[
    {
        "step": "transform",
        "status": "completed",
        "start_time": 1730223952.345782,
        "end_time": 1730223953.457916,
        "duration": 1,
        "input_files": [
            {
                "key": "raw_data",
                "rows": 5
            }
        ],
        "output_files": [
            {
                "key": "raw_location",
                "rows": 5
            },
            {
                "key": "raw_current",
                "rows": 5
            },
            {
                "key": "raw_forecast",
                "rows": 15
            }
        ],
        "error": null,
        "timestamp": "2024-10-29T23:15:53.457931",
        "stacktrace": null
    }
]